satimaclassify/__init__.py
satimaclassify/classification.py
tests/__init__.py
tests/test_classification.py
satimaclassify-1.1.0.dist-info/METADATA
satimaclassify-1.1.0.dist-info/WHEEL
satimaclassify-1.1.0.dist-info/top_level.txt
satimaclassify-1.1.0.dist-info/RECORD
