Metadata-Version: 2.1
Name: satimaclassify
Version: 1.1.0
Summary: A package for satellite image classification(SatImaCla)
Home-page: https://github.com/your_username/satellite_image_classification
Author: b0814
Author-email: b0814@n-koei.co.jp
Classifier: Programming Language :: Python :: 3
Classifier: License :: OSI Approved :: MIT License
Classifier: Operating System :: OS Independent
Requires-Python: >=3.6
Requires-Dist: rasterio
Requires-Dist: numpy
Requires-Dist: scikit-learn
Requires-Dist: fiona
Requires-Dist: matplotlib
Requires-Dist: pandas
Requires-Dist: joblib
